rtl/d_mem.sv
module d_mem #(
    parameter   ADDRESS_WIDTH =32,
                DATA_WIDTH = 32
) (
    input logic [ADDRESS_WIDTH-1:0] addr,
    input logic [DATA_WIDTH-1:0] wd,
    input logic clk,
    input logic we,
    output logic [DATA_WIDTH-1:0] rd
);

logic [DATA_WIDTH-1:0] mem_array [10*ADDRESS_WIDTH-1:0];

always_ff @(posedge clk) begin
    if (we == 1'b1) begin
        mem_array[addr] = wd;
    end
end

always_comb begin
    rd = mem_array[addr];
end
    
endmodule

rtl/extend.sv
module extend(
    input logic [31:7] imm,
    input logic [2:0] immsrc,
    output logic [31:0] immext
);

typedef enum logic[2:0] {  
    TYPE_R = 3'b000,
    TYPE_I = 3'b001,
    TYPE_S = 3'b010,
    TYPE_B = 3'b011,
    TYPE_U = 3'b100,
    TYPE_J = 3'b101
} imm_src_sel;

always_comb begin
    case(immsrc)
        TYPE_I:begin
            immext = {{20{imm[31]}},imm[31:20]};
        end
        TYPE_S:begin
            immext = {{20{imm[31]}},{imm[31:25],imm[11:7]}};
        end 
        TYPE_B:begin
            immext = {{19{imm[31]}},{imm[31],imm[7],imm[30:25],imm[11:8],1'b0}};
        end
        TYPE_U:begin
            immext = {{12{imm[31]}},{imm[31:12]}};
            immext = immext << 12;
        end
        TYPE_J:begin
            immext = {{11{imm[31]}},{imm[31],imm[19:12],imm[20],imm[30:21],1'b0}};
            immext = immext << 1;
        end
        default:begin
            immext = '0;
        end
    endcase
end
    
endmodule

rtl/decoder.sv
module decoder(
    input logic [6:0] op,
    input logic [2:0] func3,
    input logic funct7,
    input logic zero, 
    output logic PCSrc,
    output logic ResultSrc,
    output logic Memwrite,
    output logic [3:0] ALUControl,
    output logic ALUSrc,
    output logic [2:0] ImmSrc,
    output logic regwrite
);

typedef enum logic[2:0] {
    IMM_I = 3'b001,
    IMM_S = 3'b010,
    IMM_B = 3'b011,
    IMM_U = 3'b100
} imm_src_t;

typedef enum logic [3:0] {
    ALU_ADD  = 4'b0000,
    ALU_SUB  = 4'b0001,
    ALU_SLL  = 4'b0010,
    ALU_SLT  = 4'b0011,
    ALU_SLTU = 4'b0100,
    ALU_XOR  = 4'b0101,
    ALU_SRL  = 4'b0110,
    ALU_SRA  = 4'b0111,
    ALU_OR   = 4'b1000,
    ALU_AND  = 4'b1001
} alu_ctrl_t;


typedef enum logic [6:0] { 
    LW = 7'b0000011,
    SW = 7'b0100011,
    RTYPE = 7'b0110011,
    BEQ = 7'b1100011,
    ITYPE = 7'b0010011
} opcodes;

typedef enum logic[2:0]{
    offset = 3'b00,
    sub = 3'b01,
    rtype = 3'b10,
    jump = 3'b11
}alu_op_cases;

logic [1:0] AluOp;

logic Branch;

always_comb begin
    case(op)
        LW: begin
            regwrite    = 1'b1;
            ImmSrc      = IMM_I;
            ALUSrc      = 1'b1;
            Memwrite    = 1'b0;
            ResultSrc   = 1'b1;
            Branch      = 1'b0;
            AluOp       = offset;
        end

        SW: begin
            regwrite    = 1'b0;
            ImmSrc      = IMM_S;
            ALUSrc      = 1'b1;
            Memwrite    = 1'b1;
            ResultSrc   = 'x; //don't care
            Branch      = 1'b0;
            AluOp       = offset;
        end

        RTYPE: begin
            regwrite    = 1'b1;
            ImmSrc      = 'x; //don't care
            ALUSrc      = 1'b0;
            Memwrite    = 1'b0;
            ResultSrc   = 1'b0; 
            Branch      = 1'b0;
            AluOp       = rtype;
        end

        ITYPE: begin
            regwrite    = 1'b1;
            ImmSrc      = 1'b1; 
            ALUSrc      = 1'b1;
            Memwrite    = 1'b0;
            ResultSrc   = 1'b0; 
            Branch      = 1'b0;
            AluOp       = rtype;
        end

        BEQ: begin
            regwrite    = 1'b0;
            ImmSrc      = IMM_B; 
            ALUSrc      = 1'b0;
            Memwrite    = 1'b0;
            ResultSrc   = 'x; //don't care
            Branch      = 1'b1;
            AluOp       = jump;
        end
        default:begin
            regwrite    = 1'b0;
            ImmSrc      = 2'b0; 
            ALUSrc      = 1'b0;
            Memwrite    = 1'b0;
            ResultSrc   = 1'b0; 
            Branch      = 1'b0;
            AluOp       = 2'b0;
        end
    endcase

    case(AluOp)
        offset:begin
            ALUControl = 4'b0000; //add 
        end
        jump:begin
            ALUControl = 4'b0001; //sub
        end
        rtype: begin 
            case(func3)
                3'b000:begin 
                    case({op[5],funct7})
                        2'b11: begin
                            ALUControl = ALU_SUB; //sub
                        end
                        2'b10:begin
                            ALUControl = ALU_ADD; //add
                        end
                        default: begin
                            ALUControl = ALU_ADD;// add
                        end
                    endcase
                end
                3'b001: begin
                    ALUControl = ALU_SLL;//sll
                end
                3'b010:begin
                    ALUControl = ALU_SLT; //slt 
                end
                3'b011: begin
                    ALUControl = ALU_SLTU; //sltu
                end
                3'b100: begin
                    ALUControl = ALU_XOR; //xor
                end
                3'b101:begin
                    case({op[5],funct7})
                        2'b11: begin
                            ALUControl = ALU_SRL; //srl
                        end
                        2'b10:begin
                            ALUControl = ALU_SRA; //sra
                        end
                        default: begin
                            ALUControl = ALU_SRL;// srl
                        end
                    endcase                end
                3'b110:begin
                    ALUControl = ALU_OR; //or
                end
                3'b111:begin
                    ALUControl = ALU_AND;   //and 
                end
                default:begin
                    ALUControl = ALU_ADD; //add
                end
            endcase
        end
    endcase

    PCSrc = Branch & zero;
end

endmodule

rtl/alu.sv
module alu (
    input  logic [31:0] a, b,
    input  logic [3:0]  alu_op,
    output logic [31:0] result,
    output logic        zero       // result == 0 flag
);

typedef enum logic [3:0] {
    ADD  = 4'b0000,
    SUB  = 4'b0001,
    SLL  = 4'b0010,
    SLT  = 4'b0011,
    SLTU = 4'b0100,
    XOR  = 4'b0101,
    SRL  = 4'b0110,
    SRA  = 4'b0111,
    OR   = 4'b1000,
    AND  = 4'b1001
} alu_ctrl_t;


always_comb begin
    case (alu_op)
        ADD: begin 
            result = a+b;
        end
        SUB: begin 
            result = a-b;
        end
        AND: begin 
            result = a&b;
        end
        OR: begin 
            result = a|b;
        end
        XOR: begin 
            result = a^b;
        end
        SLT: begin 
            if($signed(a)<$signed(b))begin
                result = 32'b1;
            end 
            else begin
                result = 32'b0;
            end
        end
        SLTU: begin 
            if(a<b)begin
                result = 32'b1;
            end 
            else begin
                result = 32'b0;
            end
        end
        SLL: begin 
            result = a<<b[4:0];
        end
        SRL: begin 
            result = a>>b[4:0];
        end
        SRA: begin 
            result = $signed(a)>>>$signed(b[4:0]);
        end
        default: result = a;
    endcase
    zero = (result == '0);
end


endmodule

rtl/regfile.sv
module regfile (
    input  logic        clk,
    input  logic        we,         // write enable
    input  logic [4:0]  ra1, ra2,   // read addresses (2 ports)
    input  logic [4:0]  wa,         // write address
    input  logic [31:0] wd,         // write data
    output logic [31:0] rd1, rd2    // read data (2 ports)
);
    logic [31:0] registers [0:31];

    always_comb begin
        if(ra1 =='0) begin
            rd1 = '0;
        end
        else if(ra2 == '0) begin
            rd2 = '0;
        end
        else begin
            rd1 = registers[ra1];
            rd2 = registers[ra2];
        end
    end

    always_ff@(posedge clk)begin
        if(we)begin
            if(wa != '0)begin
                registers[wa] <= wd;
            end
        end
    end

endmodule

rtl/instr_mem.sv
module instr_mem #(
    parameter       ADDRESS_WIDTH = 32,
                    DATA_WIDTH = 32
)(
    input logic [ADDRESS_WIDTH-1:0] addr,
    output logic [DATA_WIDTH-1:0] dout
);

logic [DATA_WIDTH-1:0] instr_array [10*ADDRESS_WIDTH-1:0];

initial begin
    $display("Loading instr...");
    $readmemh("programs/riscv.mem", instr_array);
    /*
    Counterintutively, readmemh path is relative to the project route(or if
    all hope is lost, we use absolute paths)
    */
end

always_comb begin
    dout = instr_array[addr>>2];
    /*
    We shift left by 2 because PC incrememnts in 4s 
    but our array increments in 1s
    */
end


endmodule

rtl/cpu_top.sv
module cpu_top(
    input clk,
    input rst
);
    


logic [31:0] Pc;
logic [31:0] PcNext;
logic [31:0] Instr;
logic        RegWrite;
logic [2:0]  ImmSrc;
logic        ALUSrc;
logic [3:0]  ALUControl;
logic        Memwrite;
logic        ResultSrc;
logic        PCSrc;
logic [31:0] PCPlus4;
logic [31:0] SrcA;
logic [31:0] SrcB;
logic [31:0] ReadData;
logic [31:0] WriteData;
logic [31:0] ImmExt;
logic [31:0] PCTarget;
logic [31:0] Result;
logic  Zero;
logic [31:0] ALUResult;


always_ff @(posedge clk) begin
    if (rst) begin
        Pc <='0;
        PcNext <= '0;
    end
    else begin
        Pc <= PcNext;
    end
end


/*
Adding the muxes and adders
*/
always_comb begin
    SrcB = ALUSrc ? (ImmExt):(WriteData);
    Result = ResultSrc ? (ReadData):(ALUResult);
    PcNext = PCSrc ? (PCTarget):(PCPlus4);
    PCTarget = Pc + ImmExt;
    PCPlus4 = Pc + 4;
end

instr_mem instr_mem(
    .addr(Pc),
    .dout(Instr)
);

regfile regfile(
    .clk(clk),
    .we(RegWrite),         
    .ra1(Instr[19:15]),
    .ra2(Instr[24:20]),  
    .wa(Instr[11:7]),        
    .wd(Result),       
    .rd1(SrcA),
    .rd2(WriteData)   
);

alu alu(
    .a(SrcA),
    .b(SrcB),
    .alu_op(ALUControl),
    .result(ALUResult),
    .zero(Zero)      // result == 0 flag
);

decoder decoder (
    .op(Instr[6:0]),
    .func3(Instr[14:12]),
    .funct7(Instr[30]),
    .zero(Zero), 
    .PCSrc(PCSrc),
    .ResultSrc(ResultSrc),
    .Memwrite(Memwrite),
    .ALUControl(ALUControl),
    .ALUSrc(ALUSrc),
    .ImmSrc(ImmSrc),
    .regwrite(RegWrite)
);

extend extend (
    .imm(Instr[31:7]),
    .immsrc(ImmSrc),
    .immext(ImmExt)
);

d_mem d_mem (
    .addr(ALUResult),
    .wd(WriteData),
    .clk(clk),
    .we(Memwrite),
    .rd(ReadData)
);


endmodule

tb/tb_cpu_top.sv
module tb;
    logic clk;
    logic rst;

    cpu_top uut(.*); //ADD MODULE UNDER TEST HERE 

    always #5 clk = ~clk;


    int pass_count = 0;
    int fail_count = 0;

    task check(string name, logic [31:0] actual, logic [31:0] expected);
    if (actual !== expected) begin
        $error("%s: expected %0h, got %0h", name, expected, actual);
        fail_count++;
    end else
        pass_count++;
    endtask


    initial begin 
        $dumpfile("waves.vcd");
        $dumpvars(0,tb);
        clk = 0; rst = 1; //ADD INITIALISATION HERE
        #10;
        rst = 0;

        #200;
        
        $display("\n===== Resu  lts: %0d passed, %0d failed =====", pass_count, fail_count);

        $display("End of testing");
        #20; $finish;
    end
endmodule

waves.vcd
$date
	Wed Aug  5 10:02:54 2026
$end
$version
	Icarus Verilog
$end
$timescale
	1s
$end
$scope module tb $end
$var reg 1 ! clk $end
$var reg 1 " rst $end
$var integer 32 # fail_count [31:0] $end
$var integer 32 $ pass_count [31:0] $end
$scope module uut $end
$var wire 1 ! clk $end
$var wire 1 " rst $end
$var wire 1 % Zero $end
$var wire 32 & WriteData [31:0] $end
$var wire 32 ' SrcA [31:0] $end
$var wire 1 ( ResultSrc $end
$var wire 1 ) RegWrite $end
$var wire 32 * ReadData [31:0] $end
$var wire 1 + PCSrc $end
$var wire 1 , Memwrite $end
$var wire 32 - Instr [31:0] $end
$var wire 3 . ImmSrc [2:0] $end
$var wire 32 / ImmExt [31:0] $end
$var wire 1 0 ALUSrc $end
$var wire 32 1 ALUResult [31:0] $end
$var wire 4 2 ALUControl [3:0] $end
$var reg 32 3 PCPlus4 [31:0] $end
$var reg 32 4 PCTarget [31:0] $end
$var reg 32 5 Pc [31:0] $end
$var reg 32 6 PcNext [31:0] $end
$var reg 32 7 Result [31:0] $end
$var reg 32 8 SrcB [31:0] $end
$scope module alu $end
$var wire 32 9 b [31:0] $end
$var wire 4 : alu_op [3:0] $end
$var wire 32 ; a [31:0] $end
$var reg 32 < result [31:0] $end
$var reg 1 % zero $end
$upscope $end
$scope module d_mem $end
$var wire 32 = addr [31:0] $end
$var wire 1 ! clk $end
$var wire 1 , we $end
$var wire 32 > wd [31:0] $end
$var parameter 32 ? ADDRESS_WIDTH $end
$var parameter 32 @ DATA_WIDTH $end
$var reg 32 A rd [31:0] $end
$upscope $end
$scope module decoder $end
$var wire 3 B func3 [2:0] $end
$var wire 1 C funct7 $end
$var wire 7 D op [6:0] $end
$var wire 1 % zero $end
$var reg 4 E ALUControl [3:0] $end
$var reg 1 0 ALUSrc $end
$var reg 2 F AluOp [1:0] $end
$var reg 1 G Branch $end
$var reg 3 H ImmSrc [2:0] $end
$var reg 1 , Memwrite $end
$var reg 1 + PCSrc $end
$var reg 1 ( ResultSrc $end
$var reg 1 ) regwrite $end
$upscope $end
$scope module extend $end
$var wire 25 I imm [31:7] $end
$var wire 3 J immsrc [2:0] $end
$var reg 32 K immext [31:0] $end
$upscope $end
$scope module instr_mem $end
$var wire 32 L addr [31:0] $end
$var parameter 32 M ADDRESS_WIDTH $end
$var parameter 32 N DATA_WIDTH $end
$var reg 32 O dout [31:0] $end
$upscope $end
$scope module regfile $end
$var wire 1 ! clk $end
$var wire 5 P ra1 [4:0] $end
$var wire 5 Q ra2 [4:0] $end
$var wire 5 R wa [4:0] $end
$var wire 32 S wd [31:0] $end
$var wire 1 ) we $end
$var reg 32 T rd1 [31:0] $end
$var reg 32 U rd2 [31:0] $end
$upscope $end
$upscope $end
$scope task check $end
$var reg 32 V actual [31:0] $end
$var reg 32 W expected [31:0] $end
$upscope $end
$upscope $end
$enddefinitions $end
$comment Show the parameter values. $end
$dumpall
b100000 N
b100000 M
b100000 @
b100000 ?
$end
#0
$dumpvars
bx W
bx V
bx U
bx T
bx S
bx R
bx Q
bx P
bx O
bx L
b0 K
b0 J
bx I
b0 H
0G
b0 F
b0 E
bx D
xC
bx B
bx A
bx >
bx =
bx <
bx ;
b0 :
bx 9
bx 8
bx 7
bx 6
bx 5
bx 4
bx 3
b0 2
bx 1
00
b0 /
b0 .
bx -
0,
0+
bx *
0)
0(
bx '
bx &
x%
b0 $
b0 #
1"
0!
$end
#5
b101 7
b101 S
0%
b101 1
b101 <
b101 =
b101 8
b101 9
b101 /
b101 K
b10 F
10
b1 .
b1 H
b1 J
1)
b0 '
b0 ;
b0 T
b1010000000000010 I
0C
b0 B
b10011 D
b10 R
b101 Q
b0 P
b10100000000000100010011 -
b10100000000000100010011 O
b100 3
b101 4
b100 6
b0 5
b0 L
1!
#10
0!
0"
#15
b1100 7
b1100 S
b1100 1
b1100 <
b1100 =
b1000 6
b1100 8
b1100 9
b1100 /
b1100 K
b11000000000000011 I
b11 R
b1100 Q
b110000000000000110010011 -
b110000000000000110010011 O
b1000 3
b10000 4
b100 5
b100 L
1!
#20
0!
#25
b1100 6
b10001 7
b10001 S
b10001 1
b10001 <
b10001 =
b0 /
b0 K
00
bx .
bx H
bx J
b1100 &
b1100 >
b1100 U
b101 '
b101 ;
b101 T
b110001000000001 I
b110011 D
b1 R
b11 Q
b10 P
b1100010000000010110011 -
b1100010000000010110011 O
b1100 3
b1000 4
b1000 5
b1000 L
1!
#30
0!
#35
b10000 6
b11111111111111111111111111111001 7
b11111111111111111111111111111001 S
b11111111111111111111111111111001 1
b11111111111111111111111111111001 <
b11111111111111111111111111111001 =
b1 2
b1 :
b1 E
b100000000110001000000010 I
1C
b10 R
b1000000001100010000000100110011 -
b1000000001100010000000100110011 O
b10000 3
b1100 4
b1100 5
b1100 L
1!
#40
0!
#45
b10100 6
bx 7
bx S
b100 8
b100 9
b100 /
b100 K
b0 2
b0 :
b0 E
b0 F
x(
1,
10
b10 .
b10 H
b10 J
0)
b11111111111111111111111111111001 &
b11111111111111111111111111111001 >
b11111111111111111111111111111001 U
b10000 1
b10000 <
b10000 =
b100001101000100 I
0C
b10 B
b100011 D
b100 R
b10 Q
b11 P
b1100 '
b1100 ;
b1100 T
b1000011010001000100011 -
b1000011010001000100011 O
b10100 3
b10100 4
b10000 5
b10000 L
1!
#50
0!
#55
b11000 6
1(
0,
b1 .
b1 H
b1 J
1)
bx &
bx >
bx U
b1000001101000101 I
b11 D
b101 R
b100 Q
b10000011010001010000011 -
b10000011010001010000011 O
b11000 3
b11000 4
b10100 5
b10100 L
b11111111111111111111111111111001 7
b11111111111111111111111111111001 S
b11111111111111111111111111111001 *
b11111111111111111111111111111001 A
1!
#60
0!
#65
1+
1%
bx *
bx A
b100000 6
bx 7
bx S
b11111111111111111111111111111001 8
b11111111111111111111111111111001 9
b0 1
b0 <
b0 =
b1000 /
b1000 K
b1 2
b1 :
b1 E
b11 F
1G
x(
00
b11 .
b11 H
b11 J
0)
b11111111111111111111111111111001 &
b11111111111111111111111111111001 >
b11111111111111111111111111111001 U
b11111111111111111111111111111001 '
b11111111111111111111111111111001 ;
b11111111111111111111111111111001 T
b1010001000001000 I
b0 B
b1100011 D
b1000 R
b101 Q
b10 P
b10100010000010001100011 -
b10100010000010001100011 O
b11100 3
b100000 4
b11000 5
b11000 L
1!
#70
0!
#75
0%
b101 1
b101 <
b101 =
b100100 6
b101 7
b101 S
b1100 8
b1100 9
b0 /
b0 K
0+
b0 2
b0 :
b0 E
b10 F
0G
0(
bx .
bx H
bx J
1)
b1100 &
b1100 >
b1100 U
b110010100000011 I
b110011 D
b11 R
b11 Q
b101 P
b1100101000000110110011 -
b1100101000000110110011 O
b100100 3
b100000 4
b100000 5
b100000 L
1!
#80
0!
#85
bx 7
bx S
x%
bx 1
bx <
bx =
b0 F
b0 .
b0 H
b0 J
0)
bx '
bx ;
bx T
b101000 6
bx 8
bx 9
bx I
xC
bx B
bx D
bx R
bx Q
bx P
bx &
bx >
bx U
bx -
bx O
b101000 3
b100100 4
b100100 5
b100100 L
1!
#90
0!
#95
b101100 3
b101000 4
b101000 5
b101000 L
1!
