rtl/decoder.sv
module decoder(
    input logic [6:0] op,
    input logic [2:0] func3,
    input logic funct7,
    input logic zero, 
    output logic PCSrc,
    output logic ResultSrc,
    output logic Memwrite,
    output logic [2:0] ALUControl,
    output logic ALUSrc,
    output logic [2:0] ImmSrc,
    output logic regwrite
);

typedef enum logic[2:0] {
    IMM_I = 3'b000,
    IMM_S = 3'b001,
    IMM_B = 3'b010
  } imm_src_t;

localparam lw = 7'b0000011;
localparam sw = 7'b0100011;
localparam Rtype = 7'b0110011;
localparam beq = 7'b1100011;

localparam add = 2'b00;
localparam sub = 2'b01;
localparam alu = 2'b10;

logic [1:0] AluOp;

logic Branch;

always_comb begin
    case(op)
        lw: begin
            regwrite    = 1'b1;
            ImmSrc      = IMM_I;
            ALUSrc      = 1'b1;
            Memwrite    = 1'b0;
            ResultSrc   = 1'b1;
            Branch      = 1'b0;
            AluOp       = add;
        end

        sw: begin
            regwrite    = 1'b0;
            ImmSrc      = IMM_S;
            ALUSrc      = 1'b1;
            Memwrite    = 1'b1;
            ResultSrc   = 'x; //don't care
            Branch      = 1'b0;
            AluOp       = add;
        end

        Rtype: begin
            regwrite    = 1'b1;
            ImmSrc      = 'x; //don't care
            ALUSrc      = 1'b0;
            Memwrite    = 1'b0;
            ResultSrc   = 1'b0; 
            Branch      = 1'b0;
            AluOp       = alu;
        end

        beq: begin
            regwrite    = 1'b0;
            ImmSrc      = IMM_B; 
            ALUSrc      = 1'b0;
            Memwrite    = 1'b0;
            ResultSrc   = 'x; //don't care
            Branch      = 1'b1;
            AluOp       = sub;
        end
        default:begin
            regwrite    = 1'b0;
            ImmSrc      = 2'b0; 
            ALUSrc      = 1'b0;
            Memwrite    = 1'b0;
            ResultSrc   = 1'b0; 
            Branch      = 1'b0;
            AluOp       = 2'b0;
        end
    endcase

    case(AluOp)
        add:begin
            ALUControl = 3'b000;
        end
        sub:begin
            ALUControl = 3'b001;
        end
        alu: begin 
            case(func3)
                3'b000:begin 
                    case({op[5],funct7})
                        2'b11: begin
                            ALUControl = 3'b001;
                        end
                        default: begin
                            ALUControl = 3'b000;
                        end
                    endcase
                end
                3'b010:begin
                    ALUControl = 3'b101;
                end
                3'b110:begin
                    ALUControl = 3'b011;
                end
                3'b111:begin
                    ALUControl = 3'b010;
                end
                default:begin
                    ALUControl = 3'b000;
                end
            endcase
        end
    endcase

    PCSrc = Branch & zero;
end

endmodule

tb/tb_decoder.sv
module tb;
    logic [6:0] op;
    logic [2:0] func3;
    logic funct7;
    logic zero; 
    logic clk;
    logic PCSrc;
    logic ResultSrc;
    logic Memwrite;
    logic [2:0] ALUControl;
    logic ALUSrc;
    logic [2:0] ImmSrc;
    logic regwrite;


    decoder uut(.*);

    always #5 clk = ~clk;

    localparam lw = 7'b0000011;
    localparam sw = 7'b0100011;
    localparam Rtype = 7'b0110011;
    localparam beq = 7'b1100011;

    int pass_count = 0;
    int fail_count = 0;

    task check(string name, logic [31:0] actual, logic [31:0] expected);
    if (actual !== expected) begin
        $error("%s: expected %0h, got %0h", name, expected, actual);
        fail_count++;
    end else
        pass_count++;
    endtask


    initial begin 
        $dumpfile("waves.vcd");
        $dumpvars(0,tb);
        op = '0; func3 = '0; funct7 = '0; zero = 1;  

        /*
        LW test:
        Regwrite : 1 - We want to load word into register
        ImmSrc: 0 - lw is I type 
        ALUSrc: 1 - We want the immediate hence our MUX takes the extended imm
        Memwrite: 0 - we want to load not store to mem
        ResultSrc: 1 - We're reading from memory hence we take the memory output
        ALUControl : 0 - lw is a positive offset hence the ALU does an add operation
        PCSrc : 0 - we're not branching hence PCSrc is 0
        */

        #20; op = lw; func3 = '0; funct7 = '0; zero = '0;
        #20;
        check("LW RegWrite",   regwrite,   1);
        check("LW ImmSrc",     ImmSrc,     0);
        check("LW ALUSrc",     ALUSrc,     1);
        check("LW MemWrite",   Memwrite,   0);
        check("LW ResultSrc",  ResultSrc,  1);
        check("LW ALUControl", ALUControl, 0);
        check("LW PCSrc",      PCSrc,      0);

        /*
        sw test:
        Regwrite : 0 - Not Writing to a register
        ImmSrc: 1 - sw is S-type 
        ALUSrc: 1 - We're calcuating integer offset from an addresshence we want the immediate
        Memwrite: 1 - We store the word in memory hence memwrite high
        ResultSrc: X - ResultSrc is fed into a mux to decide the output of result but 
        since we do a store, we don't care if the output is stored in the regfile
        ALUControl : 0 - offset hence we add 
        PCSrc : 0 - we're not branching hence PCSrc is 0
        */
        #20; op = sw; func3 = '0; funct7 = '0; zero = '0;
        #20;

        check("SW RegWrite",   regwrite,   0);
        check("SW ImmSrc",     ImmSrc,     1);
        check("SW ALUSrc",     ALUSrc,     1);
        check("SW MemWrite",   Memwrite,   1);
      //  check("SW ResultSrc",  ResultSrc,  'x);
        check("SW ALUControl", ALUControl, 0);
        check("SW PCSrc",      PCSrc,      0);

        /*
        Rtype add test:
        Regwrite : 1 - We want to write to a register
        ImmSrc: X - we're not using it's output so it can be whatever
        ALUSrc: 0 - Our ALU input is from the regfile not the imm
        Memwrite: 0 - We're storing values into regs not mem
        ResultSrc: 0 -we're reading from ALU output
        ALUControl : 0 - func3 is 0, op[5] and func7 is 0
        PCSrc : 0 - we're not branching hence PCSrc is 0
        */
        #20; op = Rtype; func3 = '0; funct7 = '0; zero = '0;
        #20;

        check("R-type add RegWrite",   regwrite,   1);
       // check("R-type add ImmSrc",     ImmSrc,     'x);
        check("R-type add ALUSrc",     ALUSrc,     0);
        check("R-type add MemWrite",   Memwrite,   0);
        check("R-type add ResultSrc",  ResultSrc,  0);
        check("R-type add ALUControl", ALUControl, 0);
        check("R-type add PCSrc",      PCSrc,      0);

        /*
        Rtype sub test:
        Same outputs except ALUControl
        */
        #20; op = Rtype; func3 = '0; funct7 = '1; zero = '0;
        #20;

        check("R-type sub RegWrite",   regwrite,   1);
      //  check("R-type sub ImmSrc",     ImmSrc,     'x);
        check("R-type sub ALUSrc",     ALUSrc,     0);
        check("R-type sub MemWrite",   Memwrite,   0);
        check("R-type sub ResultSrc",  ResultSrc,  0);
        check("R-type sub ALUControl", ALUControl, 1);
        check("R-type sub PCSrc",      PCSrc,      0);

        /*
        Rtype AND test:
        Same outputs except ALUControl
        */
        #20; op = Rtype; func3 = 3'b111; funct7 = '0; zero = '0;
        #20;

        check("R-type AND RegWrite",   regwrite,   1);
    //  check("R-type AND ImmSrc",     ImmSrc,     'x);
        check("R-type AND ALUSrc",     ALUSrc,     0);
        check("R-type AND MemWrite",   Memwrite,   0);
        check("R-type AND ResultSrc",  ResultSrc,  0);
        check("R-type AND ALUControl", ALUControl, 3'b010);
        check("R-type AND PCSrc",      PCSrc,      0);

        /*
        Rtype OR test:
        Same outputs except ALUControl
        */
        #20; op = Rtype; func3 = 3'b110; funct7 = '0; zero = '0;
        #20;

        check("R-type OR RegWrite",   regwrite,   1);
    //  check("R-type OR ImmSrc",     ImmSrc,     'x);
        check("R-type OR ALUSrc",     ALUSrc,     0);
        check("R-type OR MemWrite",   Memwrite,   0);
        check("R-type OR ResultSrc",  ResultSrc,  0);
        check("R-type OR ALUControl", ALUControl, 3'b011);
        check("R-type OR PCSrc",      PCSrc,      0);


        /*
        BEQ test:
        Regwrite : 0 - There is no destination register
        ImmSrc: 2 - BEQ is B type
        ALUSrc: 0 - Our ALU input is from the regfile not the imm
        Memwrite: x - Due to being a branch, we don't write any output to memory
        ResultSrc: 0 - We don't want to accidentally write garbage
        ALUControl : 5 - we check for equality through an AND condition
        PCSrc : 1 - we're branching hence PCSrc is 1
        */
        #20; op = beq; func3 = 3'b010; funct7 = '0; zero = 1;
        #20;

        check("BEQ TRUE RegWrite",   regwrite,   0);
        check("BEQ TRUE ImmSrc",     ImmSrc,     2);
        check("BEQ TRUE ALUSrc",     ALUSrc,     0);
        check("BEQ TRUE MemWrite",   Memwrite,   0);
     // check("BEQ TRUE ResultSrc",  ResultSrc,  'x);
        check("BEQ TRUE ALUControl", ALUControl, 1);
        check("BEQ TRUE PCSrc",      PCSrc,      1);

        //Check to see if we avoid branching when condition false
        #20; op = beq; func3 = 3'b010; funct7 = '0; zero = 0;
        #20;

        check("BEQ FALSE RegWrite",   regwrite,   0);
        check("BEQ FALSE ImmSrc",     ImmSrc,     2);
        check("BEQ FALSE ALUSrc",     ALUSrc,     0);
        check("BEQ FALSE MemWrite",   Memwrite,   0);
     // check("BEQ FALSE ResultSrc",  ResultSrc,  'x);
        check("BEQ FALSE ALUControl", ALUControl, 1);
        check("BEQ FALSE PCSrc",      PCSrc,      0);

        $display("\n===== Results: %0d passed, %0d failed =====", pass_count, fail_count);

        $display("End of testing");
        #20; $finish;
    end
endmodule

waves.vcd
$date
	Mon Aug  3 12:37:07 2026
$end
$version
	Icarus Verilog
$end
$timescale
	1s
$end
$scope module tb $end
$var wire 1 ! regwrite $end
$var wire 1 " ResultSrc $end
$var wire 1 # PCSrc $end
$var wire 1 $ Memwrite $end
$var wire 3 % ImmSrc [2:0] $end
$var wire 1 & ALUSrc $end
$var wire 3 ' ALUControl [2:0] $end
$var parameter 7 ( Rtype $end
$var parameter 7 ) beq $end
$var parameter 7 * lw $end
$var parameter 7 + sw $end
$var reg 1 , clk $end
$var reg 3 - func3 [2:0] $end
$var reg 1 . funct7 $end
$var reg 7 / op [6:0] $end
$var reg 1 0 zero $end
$var integer 32 1 fail_count [31:0] $end
$var integer 32 2 pass_count [31:0] $end
$scope module uut $end
$var wire 3 3 func3 [2:0] $end
$var wire 1 . funct7 $end
$var wire 7 4 op [6:0] $end
$var wire 1 0 zero $end
$var parameter 7 5 Rtype $end
$var parameter 2 6 add $end
$var parameter 2 7 alu $end
$var parameter 7 8 beq $end
$var parameter 7 9 lw $end
$var parameter 2 : sub $end
$var parameter 7 ; sw $end
$var reg 3 < ALUControl [2:0] $end
$var reg 1 & ALUSrc $end
$var reg 2 = AluOp [1:0] $end
$var reg 1 > Branch $end
$var reg 3 ? ImmSrc [2:0] $end
$var reg 1 $ Memwrite $end
$var reg 1 # PCSrc $end
$var reg 1 " ResultSrc $end
$var reg 1 ! regwrite $end
$upscope $end
$scope task check $end
$var reg 32 @ actual [31:0] $end
$var reg 32 A expected [31:0] $end
$upscope $end
$upscope $end
$enddefinitions $end
$comment Show the parameter values. $end
$dumpall
b100011 ;
b1 :
b11 9
b1100011 8
b10 7
b0 6
b110011 5
b100011 +
b11 *
b1100011 )
b110011 (
$end
#0
$dumpvars
bx A
bx @
b0 ?
0>
b0 =
b0 <
b0 4
b0 3
b0 2
b0 1
10
b0 /
0.
b0 -
x,
b0 '
0&
b0 %
0$
0#
0"
0!
$end
#20
1"
1&
1!
00
b11 /
b11 4
#40
b111 2
b0 A
b0 @
#60
x"
1$
b1 %
b1 ?
0!
b100011 /
b100011 4
#80
b0 A
b0 @
b1101 2
#100
b10 =
0"
0$
0&
bx %
bx ?
1!
b110011 /
b110011 4
#120
b10011 2
b0 A
b0 @
#140
b1 '
b1 <
1.
#160
b11001 2
b0 A
b0 @
#180
b10 '
b10 <
0.
b111 -
b111 3
#200
b11111 2
b0 A
b0 @
#220
b11 '
b11 <
b110 -
b110 3
#240
b100101 2
b0 A
b0 @
#260
1#
b1 '
b1 <
b1 =
1>
x"
b10 %
b10 ?
0!
10
b10 -
b10 3
b1100011 /
b1100011 4
#280
b1 A
b1 @
b101011 2
#300
0#
00
#320
b110001 2
b0 A
b0 @
