rtl/instr_mem.sv
module instr_mem #(
    parameter       ADDRESS_WIDTH = 32,
                    DATA_WIDTH = 32
)(
    input logic [ADDRESS_WIDTH-1:0] addr,
    output logic [DATA_WIDTH-1:0] dout
);

logic [DATA_WIDTH-1:0] instr_array [10*ADDRESS_WIDTH-1:0];

initial begin
    $display("Loading instr...");
    $readmemh("rtl/riscv.mem", instr_array);
end

always_comb begin
    dout = instr_array[addr>>2];
end


endmodule

tb/tb_instr_mem.sv
module tb;
    parameter       ADDRESS_WIDTH = 32;
    parameter       DATA_WIDTH = 32;

    logic [ADDRESS_WIDTH-1:0] addr;
    logic [DATA_WIDTH-1:0] dout;
    logic clk;


    instr_mem uut(.*);

    always #5 clk = ~clk;


    int pass_count = 0;
    int fail_count = 0;

    task check(string name, logic [31:0] actual, logic [31:0] expected);
    if (actual !== expected) begin
        $error("%s: expected %0h, got %0h", name, expected, actual);
        fail_count++;
    end else
        pass_count++;
    endtask


    initial begin 
        $dumpfile("waves.vcd");
        $dumpvars(0,tb);

        #20; addr = 0;
        #10; 
        check("Addr 0", dout, 32'h00500113);

        #20; addr = 4;
        #10; 
        check("Addr 0", dout, 32'h00C00193);

        #20; addr = 8;
        #10; 
        check("Addr 0", dout, 32'h003100B3);

        #20; addr = 12;
        #10; 
        check("Addr 0", dout, 32'h40310133);
        
        #20; addr = 16;
        #10; 
        check("Addr 0", dout, 32'h0021A233);
        
        #20; addr = 20;
        #10; 
        check("Addr 0", dout, 32'h0041A283);
        
        #20; addr = 24;
        #10; 
        check("Addr 0", dout, 32'h00510463);
        
        #20; addr = 28;
        #10; 
        check("Addr 0", dout, 32'h00000013);
        
        #20; addr = 32;
        #10; 
        check("Addr 0", dout, 32'h006281B3);
        
        
        $display("\n===== Results: %0d passed, %0d failed =====", pass_count, fail_count);

        $display("End of testing");
        #20; $finish;
    end
endmodule

waves.vcd
$date
	Tue Aug  4 10:32:41 2026
$end
$version
	Icarus Verilog
$end
$timescale
	1s
$end
$scope module tb $end
$var wire 32 ! dout [31:0] $end
$var parameter 32 " ADDRESS_WIDTH $end
$var parameter 32 # DATA_WIDTH $end
$var reg 32 $ addr [31:0] $end
$var reg 1 % clk $end
$var integer 32 & fail_count [31:0] $end
$var integer 32 ' pass_count [31:0] $end
$scope module uut $end
$var wire 32 ( addr [31:0] $end
$var parameter 32 ) ADDRESS_WIDTH $end
$var parameter 32 * DATA_WIDTH $end
$var reg 32 + dout [31:0] $end
$upscope $end
$scope task check $end
$var reg 32 , actual [31:0] $end
$var reg 32 - expected [31:0] $end
$upscope $end
$upscope $end
$enddefinitions $end
$comment Show the parameter values. $end
$dumpall
b100000 *
b100000 )
b100000 #
b100000 "
$end
#0
$dumpvars
bx -
bx ,
bx +
bx (
b0 '
b0 &
x%
bx $
bx !
$end
#20
b10100000000000100010011 !
b10100000000000100010011 +
b0 $
b0 (
#30
b1 '
b10100000000000100010011 -
b10100000000000100010011 ,
#50
b110000000000000110010011 !
b110000000000000110010011 +
b100 $
b100 (
#60
b10 '
b110000000000000110010011 -
b110000000000000110010011 ,
#80
b1100010000000010110011 !
b1100010000000010110011 +
b1000 $
b1000 (
#90
b11 '
b1100010000000010110011 -
b1100010000000010110011 ,
#110
b1000000001100010000000100110011 !
b1000000001100010000000100110011 +
b1100 $
b1100 (
#120
b100 '
b1000000001100010000000100110011 -
b1000000001100010000000100110011 ,
#140
b1000011010001000110011 !
b1000011010001000110011 +
b10000 $
b10000 (
#150
b101 '
b1000011010001000110011 -
b1000011010001000110011 ,
#170
b10000011010001010000011 !
b10000011010001010000011 +
b10100 $
b10100 (
#180
b110 '
b10000011010001010000011 -
b10000011010001010000011 ,
#200
b10100010000010001100011 !
b10100010000010001100011 +
b11000 $
b11000 (
#210
b111 '
b10100010000010001100011 -
b10100010000010001100011 ,
#230
b10011 !
b10011 +
b11100 $
b11100 (
#240
b1000 '
b10011 -
b10011 ,
#260
b11000101000000110110011 !
b11000101000000110110011 +
b100000 $
b100000 (
#270
b1001 '
b11000101000000110110011 -
b11000101000000110110011 ,
