rtl/alu.sv
module alu (
    input  logic [31:0] a, b,
    input  logic [3:0]  alu_op,
    output logic [31:0] result,
    output logic        zero       // result == 0 flag
);

localparam ADD  = 4'b0000;
localparam SUB  = 4'b0001;
localparam AND  = 4'b0010;
localparam OR   = 4'b0011;
localparam XOR  = 4'b0100;
localparam SLT  = 4'b0101;
localparam SLL  = 4'b0110;
localparam SRL  = 4'b0111;
localparam SRA  = 4'b1000;
localparam SLTU = 4'b1001;

always_comb begin
    case (alu_op)
        ADD: begin 
            result = a+b;
        end
        SUB: begin 
            result = a-b;
        end
        AND: begin 
            result = a&b;
        end
        OR: begin 
            result = a|b;
        end
        XOR: begin 
            result = a^b;
        end
        SLT: begin 
            if($signed(a)<$signed(b))begin
                result = 32'b1;
            end 
            else begin
                result = 32'b0;
            end
        end
        SLTU: begin 
            if(a<b)begin
                result = 32'b1;
            end 
            else begin
                result = 32'b0;
            end
        end
        SLL: begin 
            result = a<<b[4:0];
        end
        SRL: begin 
            result = a>>b[4:0];
        end
        SRA: begin 
            result = $signed(a)>>>$signed(b[4:0]);
        end
        default: result = a;
    endcase
    zero = (result == '0);
end


endmodule

tb/tb_alu.sv
module tb;
    logic [31:0] a, b;
    logic [3:0]  alu_op;
    logic [31:0] result;
    logic        clk,zero;       // result == 0 flag

    alu uut(.*);

    always #5 clk = ~clk;

    initial begin 
        $dumpfile("waves.vcd");
        $dumpvars(0,tb);
        a = 0; b = 0; alu_op = 0;

        #20; a = 32'd4; b = 32'd5;alu_op=4'b0;
        #10; $display("4 + 5 = %d(should be 9)",result);

        #20; a = 32'd4; b = 32'd5;alu_op=4'b1;
        #10; $display("4 - 5 = %d(should be -1)",result);

        #20; a = 32'b1010; b = 32'b0010;alu_op=4'b10;
        #10; $display("1010 & 0010 = %h(should be 0x2)",result);

        #20; a = 32'b1010; b = 32'b0010;alu_op=4'b11;
        #10; $display("1010 | 0010 = %h(should be 0xa)",result);

        #20; a = 32'b1010; b = 32'b0010;alu_op=4'b100;
        #10; $display("1010 ^ 0010 = %h(should be 0x8)",result);

        #20; a = 32'hFFFF1234; b = 32'b0010;alu_op=4'b101;
        #10; $display("FFFF1234 SLT 0010 = %h(should be 0x1)",result);

        #20; a = 32'hFFFF1234; b = 32'b0010;alu_op=4'b110;
        #10; $display("FFFF1234 SLL 2 = %h(should be 0xFFFC48D0)",result);

        #20; a = 32'hFFFF1234; b = 32'b0010;alu_op=4'b111;
        #10; $display("FFFF1234 SRL 2 = %h(should be 0x3fffc48d)",result);

        #20; a = 32'hFFFF1234; b = 32'b0010;alu_op=4'b1000;
        #10; $display("FFFF1234 SRA 2 = %h(should be 0xFFFFC48D)",result);
        #20; $display("Checking on zero: zero = %h",zero);

        #20; a = 32'hFFFF1234; b = 32'b0010;alu_op=4'b1001;
        #10; $display("FFFF1234 SLTU 2 = %h(should be 0)",result);

        #20; $display("Checking on zero: zero = %h",zero);
        #20; $finish;
    end
endmodule

waves.vcd
$date
	Fri Jul 31 14:11:08 2026
$end
$version
	Icarus Verilog
$end
$timescale
	1s
$end
$scope module tb $end
$var wire 1 ! zero $end
$var wire 32 " result [31:0] $end
$var reg 32 # a [31:0] $end
$var reg 4 $ alu_op [3:0] $end
$var reg 32 % b [31:0] $end
$var reg 1 & clk $end
$scope module uut $end
$var wire 32 ' a [31:0] $end
$var wire 4 ( alu_op [3:0] $end
$var wire 32 ) b [31:0] $end
$var parameter 4 * ADD $end
$var parameter 4 + AND $end
$var parameter 4 , OR $end
$var parameter 4 - SLL $end
$var parameter 4 . SLT $end
$var parameter 4 / SLTU $end
$var parameter 4 0 SRA $end
$var parameter 4 1 SRL $end
$var parameter 4 2 SUB $end
$var parameter 4 3 XOR $end
$var reg 32 4 result [31:0] $end
$var reg 1 ! zero $end
$upscope $end
$upscope $end
$enddefinitions $end
$comment Show the parameter values. $end
$dumpall
b100 3
b1 2
b111 1
b1000 0
b1001 /
b101 .
b110 -
b11 ,
b10 +
b0 *
$end
#0
$dumpvars
b0 4
b0 )
b0 (
b0 '
x&
b0 %
b0 $
b0 #
b0 "
1!
$end
#20
0!
b1001 "
b1001 4
b101 %
b101 )
b100 #
b100 '
#50
b11111111111111111111111111111111 "
b11111111111111111111111111111111 4
b1 $
b1 (
#80
b10 "
b10 4
b10 $
b10 (
b10 %
b10 )
b1010 #
b1010 '
#110
b1010 "
b1010 4
b11 $
b11 (
#140
b1000 "
b1000 4
b100 $
b100 (
#170
b1 "
b1 4
b101 $
b101 (
b11111111111111110001001000110100 #
b11111111111111110001001000110100 '
#200
b11111111111111000100100011010000 "
b11111111111111000100100011010000 4
b110 $
b110 (
#230
b111111111111111100010010001101 "
b111111111111111100010010001101 4
b111 $
b111 (
#260
b11111111111111111100010010001101 "
b11111111111111111100010010001101 4
b1000 $
b1000 (
#310
1!
b0 "
b0 4
b1001 $
b1001 (
